Metadata-Version: 2.1
Name: bellande_rust_executable
Version: 0.3.7
Summary: Bellande Rust Executable is a library that makes rust code into an executable (BRE) library
Author: RonaldsonBellande
Author-email: ronaldsonbellande@gmail.com
Project-URL: Home, https://github.com/Architecture-Mechanism/bellande_rust_executable
Project-URL: Homepage, https://github.com/Architecture-Mechanism/bellande_rust_executable
Project-URL: documentation, https://github.com/Architecture-Mechanism/bellande_rust_executable
Project-URL: repository, https://github.com/Architecture-Mechanism/bellande_rust_executable
Keywords: package,setuptools
Classifier: License :: OSI Approved :: GNU General Public License v3 (GPLv3)
Classifier: Programming Language :: Python
Requires-Python: >=3.0
License-File: LICENSE
Requires-Dist: numpy
Provides-Extra: dev
Requires-Dist: pytest; extra == "dev"
Requires-Dist: pytest-cov[all]; extra == "dev"
Requires-Dist: mypy; extra == "dev"
Requires-Dist: black; extra == "dev"
